pyguru/__init__.py
pyguru/api.py
pyguru-0.0.3.dist-info/LICENSE
pyguru-0.0.3.dist-info/METADATA
pyguru-0.0.3.dist-info/WHEEL
pyguru-0.0.3.dist-info/top_level.txt
pyguru-0.0.3.dist-info/RECORD
