Metadata-Version: 2.1
Name: pyguru
Version: 0.0.3
Summary: Labguru API python support
Home-page: https://github.com/jteske54/pyguru
Author: jteske54
Author-email: teske.jacob@gmail.com
License: UNKNOWN
Keywords: python,labguru,pyguru,lab,guru
Platform: UNKNOWN
License-File: LICENSE
Requires-Dist: requests
Requires-Dist: pandas
Requires-Dist: numpy
